pval_corrections/__init__.py
pval_corrections/correction.py
pval_corrections-0.1.0.dist-info/licenses/LICENSE
pval_corrections-0.1.0.dist-info/METADATA
pval_corrections-0.1.0.dist-info/WHEEL
pval_corrections-0.1.0.dist-info/top_level.txt
pval_corrections-0.1.0.dist-info/RECORD
