Metadata-Version: 2.4
Name: pval-corrections
Version: 0.1.0
Summary: A Python package for statistical p-value corrections
Author: Christopher Ren
Author-email: Christopher Ren <chris.ren@emory.edu>
License: MIT
Classifier: Development Status :: 3 - Alpha
Classifier: Intended Audience :: Science/Research
Classifier: License :: OSI Approved :: MIT License
Classifier: Operating System :: OS Independent
Classifier: Programming Language :: Python :: 3
Classifier: Programming Language :: Python :: 3.8
Classifier: Programming Language :: Python :: 3.9
Classifier: Programming Language :: Python :: 3.10
Classifier: Programming Language :: Python :: 3.11
Classifier: Programming Language :: Python :: 3.12
Classifier: Topic :: Scientific/Engineering :: Mathematics
Classifier: Topic :: Scientific/Engineering :: Information Analysis
Requires-Python: >=3.8
License-File: LICENSE
Requires-Dist: pandas>=2.1.3
Requires-Dist: numpy>=2.1.3
Requires-Dist: matplotlib>=3.10.0
Requires-Dist: seaborn>=0.13.2
Requires-Dist: scipy>=1.13.0
Requires-Dist: scikit-learn>=1.3.0
Requires-Dist: statsmodels>=0.14.0
Provides-Extra: dev
Requires-Dist: pytest>=6.0; extra == "dev"
Requires-Dist: pytest-cov>=2.0; extra == "dev"
Requires-Dist: black>=21.0; extra == "dev"
Requires-Dist: flake8>=3.8; extra == "dev"
Requires-Dist: mypy>=0.800; extra == "dev"
Dynamic: author
Dynamic: license-file
Dynamic: requires-python
